mi/__init__.py
mi/mi1.c
mi/mi1.h
mi/mi_c.py
mi/mi_pd.py
libmi.cpython-311-darwin.so
text_mi-0.1.0.dist-info/LICENSE
text_mi-0.1.0.dist-info/METADATA
text_mi-0.1.0.dist-info/WHEEL
text_mi-0.1.0.dist-info/RECORD
