Metadata-Version: 2.1
Name: text-mi
Version: 0.1.0
Summary: MI calculations based on C extension for python and Pandas.
Home-page: https://github.com/volkoshkursk/MI
License: Apache-2.0 license
Author: volkoshkursk
Author-email: zaz-pagani@inbox.ru
Requires-Python: >3.8
Classifier: License :: Other/Proprietary License
Classifier: Programming Language :: Python :: 3
Classifier: Programming Language :: Python :: 3.9
Classifier: Programming Language :: Python :: 3.10
Classifier: Programming Language :: Python :: 3.11
Requires-Dist: numpy (>1.23)
Requires-Dist: pandas (>1.4)
Requires-Dist: toolz (>=0.12.0,<0.13.0)
Requires-Dist: tqdm (>4.64.0)
Project-URL: Repository, https://github.com/volkoshkursk/MI
